corut_fastapi_tools/__init__.py
corut_fastapi_tools/_content_types.py
corut_fastapi_tools-0.0.5.dist-info/LICENSE
corut_fastapi_tools-0.0.5.dist-info/METADATA
corut_fastapi_tools-0.0.5.dist-info/WHEEL
corut_fastapi_tools-0.0.5.dist-info/top_level.txt
corut_fastapi_tools-0.0.5.dist-info/RECORD
