Metadata-Version: 2.1
Name: corut-fastapi-tools
Version: 0.0.5
Summary: Includes facilitating plugins for Fastapi
Home-page: https://pypi.org/project/corut_fastapi_tools
Author: ibrahim CÖRÜT
Author-email: ibrhmcorut@gmail.com
License: MIT License
Project-URL: Documentation, https://www.ibrahimcorut.com/en/projects/pypi-corut_fastapi_tools
Project-URL: Source Code, https://www.ibrahimcorut.com/en/projects/pypi-corut_fastapi_tools
Keywords: cörüt, corut, corut_fastapi_tools, fastapi
Classifier: Framework :: FastAPI
Classifier: Intended Audience :: Developers
Classifier: License :: OSI Approved :: MIT License
Classifier: Operating System :: OS Independent
Classifier: Programming Language :: Python :: 3
Classifier: Programming Language :: Python :: 3 :: Only
Requires-Python: >=3.8
License-File: LICENSE
Requires-Dist: aiohttp
Requires-Dist: aiohttp-retry
Requires-Dist: aiofiles
Requires-Dist: asyncpg
Requires-Dist: boto3
Requires-Dist: botocore
Requires-Dist: databases
Requires-Dist: fastapi
Requires-Dist: hypercorn
Requires-Dist: importlib-metadata
Requires-Dist: openai
Requires-Dist: openpyxl
Requires-Dist: pandas
Requires-Dist: psutil
Requires-Dist: psycopg2-binary
Requires-Dist: pydantic
Requires-Dist: pyjwt
Requires-Dist: pytest
Requires-Dist: pytest-html
Requires-Dist: python-multipart
Requires-Dist: requests
Requires-Dist: sqlalchemy
Requires-Dist: starlette
Requires-Dist: uvicorn
Requires-Dist: pytz
